src/memory/data_mem.v
module data_mem(
    input clk,
    input mem_read,
    input mem_write,
    input [7:0] address,
    input [7:0] write_data,
    output reg [7:0] read_data
);

    reg [7:0] mem [0:255];
    integer i;

    initial begin
        for (i = 0; i < 256; i = i + 1) mem[i] = 8'h00;
    end

    always @(posedge clk) begin
        if (mem_write) begin
            mem[address] <= write_data;
        end
    end

    always @(*) begin
        if (mem_read) read_data = mem[address];
        else read_data = 8'h00;
    end

endmodule

src/encryption/xor_enc.v
module xor_enc(
    input  wire [7:0] data_in,
    input  wire [7:0] key,
    output wire [7:0] data_out
);
    assign data_out = data_in ^ key;
endmodule

src/alu.v
module alu(
    input enable,
    input [3:0] opcode,
    input [7:0] a,
    input [7:0] b,
    output reg [7:0] result
);

    always @(*) begin
        if (!enable) result = 8'h00;
        else begin
            case(opcode)
                4'b0001: result = a + b;
                4'b0010: result = a - b;
                4'b0011: result = a ^ b;
                4'b0100: result = b;
                default: result = 8'h00;
            endcase
        end
    end

endmodule

src/regfile.v
module regfile(
    input clk,
    input reset,
    input reg_write,
    input [3:0] rs1,
    input [3:0] rs2,
    input [3:0] rd,
    input [7:0] write_data,
    output reg [7:0] out_rs1,
    output reg [7:0] out_rs2
);

    reg [7:0] regs [0:15];
    integer i;    // letakkan di sini

    always @(posedge clk or posedge reset) begin
        if (reset) begin
            for (i = 0; i < 16; i = i + 1) regs[i] <= 0;
        end else if (reg_write) begin
            regs[rd] <= write_data;
        end
    end

    always @(*) begin
        out_rs1 = regs[rs1];
        out_rs2 = regs[rs2];
    end

endmodule

src/control_unit.v
module control_unit(
    input clk,
    input reset,
    input [3:0] opcode,
    output reg reg_write,
    output reg mem_read,
    output reg mem_write,
    output reg alu_enable,
    output reg pc_enable,
    output reg halt,
    output reg [2:0] state
);

    localparam S_FETCH     = 3'd0;
    localparam S_DECODE    = 3'd1;
    localparam S_EXECUTE   = 3'd2;
    localparam S_MEM       = 3'd3;
    localparam S_WRITEBACK = 3'd4;
    localparam S_HALT      = 3'd5;

    reg [2:0] next_state;

    always @(posedge clk or posedge reset) begin
        if (reset) state <= S_FETCH;
        else state <= next_state;
    end

    always @(*) begin
        next_state = state;
        case (state)
            S_FETCH:    next_state = S_DECODE;
            S_DECODE:   next_state = S_EXECUTE;
            S_EXECUTE: begin
                case (opcode)
                    4'b0011: next_state = S_MEM;
                    4'b0100: next_state = S_MEM;
                    4'b1000: next_state = S_WRITEBACK;
                    4'b1111: next_state = S_HALT;
                    default: next_state = S_WRITEBACK;
                endcase
            end
            S_MEM:       next_state = S_WRITEBACK;
            S_WRITEBACK: next_state = S_FETCH;
            S_HALT:      next_state = S_HALT;
            default:     next_state = S_FETCH;
        endcase
    end

    always @(*) begin
        reg_write  = 0;
        mem_read   = 0;
        mem_write  = 0;
        alu_enable = 0;
        pc_enable  = 0;
        halt       = 0;

        pc_enable = (state == S_FETCH);

        if (state == S_EXECUTE) begin
            if (opcode == 4'b1000) alu_enable = 1'b1;
            else if (opcode != 4'b0011 && opcode != 4'b0100 && opcode != 4'b1111)
                alu_enable = 1'b1;
        end

        if (next_state == S_MEM) begin
            if (opcode == 4'b0011) mem_read  = 1'b1;
            else if (opcode == 4'b0100) mem_write = 1'b1;
        end

        if (next_state == S_WRITEBACK) begin
            if (opcode != 4'b0100 && opcode != 4'b1111)
                reg_write = 1'b1;
        end

        halt = (next_state == S_HALT);

    end

endmodule

src/memory/instr_mem.v
module instr_mem(
    input  [7:0] address,
    output reg [15:0] instruction
);

    always @(*) begin
        case(address)
            8'd0: instruction = 16'b1000_0001_0010_0011;
            8'd1: instruction = 16'b0000_0000_0000_0000;
            8'd2: instruction = 16'b0000_0000_0000_0000;
            8'd3: instruction = 16'b1111_0000_0000_0000;
            default: instruction = 16'b1111_0000_0000_0000;
        endcase
    end
endmodule

src/pc.v
module pc(
    input clk,
    input reset,
    input pc_enable,
    output reg [7:0] pc
);

    always @(posedge clk or posedge reset) begin
        if (reset) pc <= 0;
        else if (pc_enable) pc <= pc + 1;
    end

endmodule

src/cpu.v
module cpu(
    input clk,
    input reset,
    output wire halted
);

    wire [7:0] pc;
    wire pc_enable;

    pc pc_inst(
        .clk(clk),
        .reset(reset),
        .pc_enable(pc_enable),
        .pc(pc)
    );

    wire [15:0] instruction;
    instr_mem instr_mem_inst(
        .address(pc),
        .instruction(instruction)
    );

    wire [3:0] opcode = instruction[15:12];
    wire [3:0] rd     = instruction[11:8];
    wire [3:0] rs1    = instruction[7:4];
    wire [3:0] rs2    = instruction[3:0];

    wire reg_write;
    wire mem_read;
    wire mem_write;
    wire alu_enable;
    wire halt_signal;
    wire [2:0] state;

    control_unit cu_inst(
        .clk(clk),
        .reset(reset),
        .opcode(opcode),
        .reg_write(reg_write),
        .mem_read(mem_read),
        .mem_write(mem_write),
        .alu_enable(alu_enable),
        .pc_enable(pc_enable),
        .halt(halt_signal),
        .state(state)
    );

    assign halted = halt_signal;

    wire [7:0] reg_rs1;
    wire [7:0] reg_rs2;
    wire [7:0] reg_write_data;

    regfile regfile_inst(
        .clk(clk),
        .reset(reset),
        .reg_write(reg_write),
        .rs1(rs1),
        .rs2(rs2),
        .rd(rd),
        .write_data(reg_write_data),
        .out_rs1(reg_rs1),
        .out_rs2(reg_rs2)
    );

    wire [7:0] alu_result;
    alu alu_inst(
        .enable(alu_enable),
        .opcode(opcode),
        .a(reg_rs1),
        .b(reg_rs2),
        .result(alu_result)
    );

    wire [7:0] crypto_out;
    xor_enc xor_inst(
        .data_in(reg_rs1),
        .key(reg_rs2),
        .data_out(crypto_out)
    );

    wire [7:0] alu_selected = (opcode == 4'b1000) ? crypto_out : alu_result;

    wire [7:0] data_out;
    data_mem data_mem_inst(
        .clk(clk),
        .mem_read(mem_read),
        .mem_write(mem_write),
        .address({4'b0000, rd}),
        .write_data(reg_rs1),
        .read_data(data_out)
    );

    assign reg_write_data = mem_read ? data_out : alu_selected;

endmodule

tests/tb_cpu.v
`timescale 1ns/1ps

module tb_cpu;

reg clk;
reg reset;

integer f_in;
integer f_bin;
integer f_hex;
integer c;

integer total_cycles = 0;
integer instruction_count = 0;

real CPI;
real exec_time_ns;

reg finished = 0;

cpu cpu_inst(
    .clk(clk),
    .reset(reset)
);

wire [7:0] pc        = cpu_inst.pc;
wire [15:0] instr    = cpu_inst.instruction;
wire [2:0] state     = cpu_inst.state;
wire halted          = cpu_inst.halted;

initial begin
    clk = 0;
    forever #5 clk = ~clk;
end

initial begin
    $dumpfile("wave.vcd");
    $dumpvars(0, tb_cpu);
end

initial begin
    reset = 1;
    #20 reset = 0;
end

always @(posedge clk) begin
    if (!reset)
        total_cycles = total_cycles + 1;
end

always @(posedge clk) begin
    if (!reset && state == 3'd0)
        instruction_count = instruction_count + 1;
end

always @(posedge clk) begin
    if (!reset)
        $display("T=%0t PC=%h INSTR=%h STATE=%0d", $time, pc, instr, state);
end

initial begin
    f_in  = $fopen("input.txt", "r");
    f_hex = $fopen("output_hex.txt", "w");
    f_bin = $fopen("output_bin.txt", "w");

    while (!$feof(f_in)) begin
        c = $fgetc(f_in);
        if (c != -1 && c != 10) begin
            $fwrite(f_hex, "%02h\n", c[7:0]);
            $fwrite(f_bin, "%08b\n", c[7:0]);
        end
    end

    $fclose(f_in);
    $fclose(f_hex);
    $fclose(f_bin);
end

always @(posedge clk) begin
    if (halted)
        finished = 1;
end

initial begin
    wait(finished);

    CPI = total_cycles * 1.0 / instruction_count;
    exec_time_ns = total_cycles * 10.0;

    $display("");
    $display("===== PERFORMANCE REPORT =====");
    $display("Instruction Count = %0d", instruction_count);
    $display("Total Cycles      = %0d", total_cycles);
    $display("CPI               = %0f", CPI);
    $display("Execution Time    = %0f ns", exec_time_ns);
    $display("=================================");

    $finish;
end

endmodule

wave.vcd
$date
	Mon Dec 01 21:23:55 2025
$end
$version
	Icarus Verilog
$end
$timescale
	1ps
$end
$scope module tb_cpu $end
$var wire 1 ! halted $end
$var wire 16 " instr [15:0] $end
$var wire 8 # pc [7:0] $end
$var wire 3 $ state [2:0] $end
$var reg 1 % clk $end
$var reg 1 & finished $end
$var reg 1 ' reset $end
$var real 1 ( CPI $end
$var integer 32 ) c [31:0] $end
$var real 1 * exec_time_ns $end
$var integer 32 + f_bin [31:0] $end
$var integer 32 , f_hex [31:0] $end
$var integer 32 - f_in [31:0] $end
$var integer 32 . instruction_count [31:0] $end
$var integer 32 / total_cycles [31:0] $end
$scope module cpu_inst $end
$var wire 1 % clk $end
$var wire 1 0 halted $end
$var wire 1 ' reset $end
$var wire 3 1 state [2:0] $end
$var wire 4 2 rs2 [3:0] $end
$var wire 4 3 rs1 [3:0] $end
$var wire 8 4 reg_write_data [7:0] $end
$var wire 1 5 reg_write $end
$var wire 8 6 reg_rs2 [7:0] $end
$var wire 8 7 reg_rs1 [7:0] $end
$var wire 4 8 rd [3:0] $end
$var wire 1 9 pc_enable $end
$var wire 8 : pc [7:0] $end
$var wire 4 ; opcode [3:0] $end
$var wire 1 < mem_write $end
$var wire 1 = mem_read $end
$var wire 16 > instruction [15:0] $end
$var wire 1 ? halt_signal $end
$var wire 8 @ data_out [7:0] $end
$var wire 8 A crypto_out [7:0] $end
$var wire 8 B alu_selected [7:0] $end
$var wire 8 C alu_result [7:0] $end
$var wire 1 D alu_enable $end
$scope module alu_inst $end
$var wire 4 E opcode [3:0] $end
$var wire 1 D enable $end
$var wire 8 F b [7:0] $end
$var wire 8 G a [7:0] $end
$var reg 8 H result [7:0] $end
$upscope $end
$scope module cu_inst $end
$var wire 1 % clk $end
$var wire 4 I opcode [3:0] $end
$var wire 1 ' reset $end
$var reg 1 D alu_enable $end
$var reg 1 ? halt $end
$var reg 1 = mem_read $end
$var reg 1 < mem_write $end
$var reg 3 J next_state [2:0] $end
$var reg 1 9 pc_enable $end
$var reg 1 5 reg_write $end
$var reg 3 K state [2:0] $end
$upscope $end
$scope module data_mem_inst $end
$var wire 8 L address [7:0] $end
$var wire 1 % clk $end
$var wire 1 = mem_read $end
$var wire 1 < mem_write $end
$var wire 8 M write_data [7:0] $end
$var reg 8 N read_data [7:0] $end
$var integer 32 O i [31:0] $end
$upscope $end
$scope module instr_mem_inst $end
$var wire 8 P address [7:0] $end
$var reg 16 Q instruction [15:0] $end
$upscope $end
$scope module pc_inst $end
$var wire 1 % clk $end
$var wire 1 9 pc_enable $end
$var wire 1 ' reset $end
$var reg 8 R pc [7:0] $end
$upscope $end
$scope module regfile_inst $end
$var wire 1 % clk $end
$var wire 8 S out_rs1 [7:0] $end
$var wire 8 T out_rs2 [7:0] $end
$var wire 4 U rd [3:0] $end
$var wire 1 5 reg_write $end
$var wire 1 ' reset $end
$var wire 4 V rs1 [3:0] $end
$var wire 4 W rs2 [3:0] $end
$var wire 8 X write_data [7:0] $end
$var integer 32 Y i [31:0] $end
$upscope $end
$scope module xor_inst $end
$var wire 8 Z data_in [7:0] $end
$var wire 8 [ data_out [7:0] $end
$var wire 8 \ key [7:0] $end
$upscope $end
$upscope $end
$upscope $end
$enddefinitions $end
#0
$dumpvars
b100000 \
b1100001 [
b1000001 Z
b10000 Y
b1100001 X
b11 W
b10 V
b1 U
b100000 T
b1000001 S
b0 R
b1000000100100011 Q
b0 P
b100000000 O
b0 N
b1000001 M
b1 L
b0 K
b1 J
b1000 I
b0 H
b1000001 G
b100000 F
b1000 E
0D
b0 C
b1100001 B
b1100001 A
b0 @
0?
b1000000100100011 >
0=
0<
b1000 ;
b0 :
19
b1 8
b1000001 7
b100000 6
05
b1100001 4
b10 3
b11 2
b0 1
00
b0 /
b0 .
b10000000000000000000000000000011 -
b10000000000000000000000000000100 ,
b10000000000000000000000000000101 +
r0 *
b11111111111111111111111111111111 )
r0 (
1'
0&
0%
b0 $
b0 #
b1000000100100011 "
0!
$end
#5000
b100000 6
b100000 F
b100000 T
b100000 \
b1000001 7
b1000001 G
b1000001 M
b1000001 S
b1000001 Z
b10000 Y
1%
#10000
0%
#15000
b100000 6
b100000 F
b100000 T
b100000 \
b1000001 7
b1000001 G
b1000001 M
b1000001 S
b1000001 Z
b10000 Y
1%
#20000
0%
0'
#25000
b0 4
b0 X
b0 A
b0 [
b0 B
b0 6
b0 F
b0 T
b0 \
b0 2
b0 W
b0 7
b0 G
b0 M
b0 S
b0 Z
b1 3
b1 V
b0 L
b0 8
b0 U
b100 ;
b100 E
b100 I
09
b10 J
b100000000010000 "
b100000000010000 >
b100000000010000 Q
b1 $
b1 1
b1 K
b1 #
b1 :
b1 P
b1 R
b1 /
b1 .
1%
#30000
0%
#35000
1<
b11 J
b10 $
b10 1
b10 K
b10 /
1%
#40000
0%
#45000
0<
b100 J
b11 $
b11 1
b11 K
b11 /
1%
#50000
0%
#55000
b0 J
b100 $
b100 1
b100 K
b100 /
1%
#60000
0%
#65000
19
b1 J
b0 $
b0 1
b0 K
b101 /
1%
#70000
0%
#75000
b0 3
b0 V
b1111 ;
b1111 E
b1111 I
b1111000000000000 "
b1111000000000000 >
b1111000000000000 Q
09
b10 J
b10 #
b10 :
b10 P
b10 R
b1 $
b1 1
b1 K
b10 .
b110 /
1%
#80000
0%
#85000
1!
10
1?
b101 J
b10 $
b10 1
b10 K
b111 /
1%
#90000
0%
#95000
1!
10
1?
b101 $
b101 1
b101 K
r80 *
r4 (
1&
b1000 /
1%
